Workbook

Sheet Historical Financials
A1: RELIANCE INDUSTRIES LTD | Historical Financials (Consolidated) | ₹ Crores
A2: Source: Screener.in | FY2017–FY2026 | All figures in ₹ Crores unless stated
A4: PROFIT & LOSS
B5: FY2017 | C5: FY2018 | D5: FY2019 | E5: FY2020 | F5: FY2021 | G5: FY2022 | H5: FY2023 | I5: FY2024 | J5: FY2025 | K5: FY2026
A6: Revenue (₹ Cr) | B6: 303954 | C6: 390823 | D6: 568337 | E6: 596679 | F6: 466307 | G6: 694673 | H6: 876396 | I6: 899041 | J6: 962820 | K6: 1055780
A7: YoY Growth (%) | B7: - | C7: =(C6/B6)-1 -> 0.28579654 | D7: =(D6/C6)-1 -> 0.45420561 | E7: =(E6/D6)-1 -> 0.0498683 | F7: =(F6/E6)-1 -> -0.21849604 | G7: =(G6/F6)-1 -> 0.48973316 | H7: =(H6/G6)-1 -> 0.26159502 | I7: =(I6/H6)-1 -> 0.025838776 | J7: =(J6/I6)-1 -> 0.070941147 | K7: =(K6/J6)-1 -> 0.096549719
A8: EBITDA (₹ Cr) | B8: 46307 | C8: 64315 | D8: 84250 | E8: 89266 | F8: 80790 | G8: 108581 | H8: 142318 | I8: 162498 | J8: 165598 | K8: 179065
A9: EBITDA Margin (%) | B9: =B8/B6 -> 0.15234871 | C9: =C8/C6 -> 0.16456299 | D9: =D8/D6 -> 0.14823951 | E9: =E8/E6 -> 0.14960473 | F9: =F8/F6 -> 0.17325496 | G9: =G8/G6 -> 0.1563052 | H9: =H8/H6 -> 0.16239006 | I9: =I8/I6 -> 0.18074593 | ... K9: =K8/K6 -> 0.16960446
A10: Depreciation & Amortisation | B10: 11646 | C10: 16706 | D10: 20934 | E10: 22203 | F10: 26572 | G10: 29782 | H10: 40303 | I10: 50832 | J10: 53136 | K10: 57688
A11: EBIT (₹ Cr) | B11: 34661 | C11: 47609 | D11: 63316 | E11: 67063 | F11: 54218 | G11: 78799 | H11: 102015 | I11: 111666 | J11: 112462 | K11: 121377
A12: EBIT Margin (%) | B12: =B11/B6 -> 0.1140337 | C12: =C11/C6 -> 0.12181729 | D12: =D11/D6 -> 0.11140573 | E12: =E11/E6 -> 0.11239377 | F12: =F11/F6 -> 0.11627104 | G12: =G11/G6 -> 0.11343323 | H12: =H11/H6 -> 0.11640286 | I12: =I11/I6 -> 0.12420568 | ... K12: =K11/K6 -> 0.11496429
A13: Interest Expense | B13: 3849 | C13: 8052 | D13: 16495 | E13: 22027 | F13: 21189 | G13: 14584 | H13: 19571 | I13: 23118 | J13: 24269 | K13: 27061
A14: Other Income | B14: 9222 | C14: 9869 | D14: 8406 | E14: 8570 | F14: 22432 | G14: 19600 | H14: 12020 | I14: 15792 | J14: 17824 | K14: 28846
A15: Profit Before Tax | B15: 40034 | C15: 49426 | D15: 55227 | E15: 53606 | F15: 55461 | G15: 83815 | H15: 94464 | I15: 104340 | J15: 106017 | K15: 123162
A16: Tax | B16: 10201 | C16: 13346 | D16: 15390 | E16: 13726 | F16: 1722 | G16: 15970 | H16: 20376 | I16: 25707 | J16: 25230 | K16: 27552
A17: PAT / Net Profit (₹ Cr) | B17: 29901 | C17: 36075 | D17: 39588 | E17: 39354 | F17: 49128 | G17: 60705 | H17: 66702 | I17: 69621 | J17: 69648 | K17: 80775
A18: PAT Margin (%) | B18: =B17/B6 -> 0.098373438 | C18: =C17/C6 -> 0.092305212 | D18: =D17/D6 -> 0.069655856 | E18: =E17/E6 -> 0.065955061 | F18: =F17/F6 -> 0.10535548 | G18: =G17/G6 -> 0.087386439 | H18: =H17/H6 -> 0.07610943 | I18: =I17/I6 -> 0.077439182 | ... K18: =K17/K6 -> 0.076507416
A19: EPS (₹) | B19: 22.1 | C19: 26.66 | D19: 29.25 | E19: 29.08 | F19: 36.3 | G19: 44.86 | H19: 49.29 | I19: 51.45 | J19: 51.47 | K19: 59.69
A21: BALANCE SHEET
B22: FY2017 | C22: FY2018 | D22: FY2019 | E22: FY2020 | F22: FY2021 | G22: FY2022 | H22: FY2023 | I22: FY2024 | J22: FY2025 | K22: FY2026
A23: Equity Share Capital | B23: 2959 | C23: 5922 | D23: 5926 | E23: 6339 | F23: 6445 | G23: 6765 | H23: 6766 | I23: 6766 | J23: 13532 | K23: 13532
A24: Reserves & Surplus | B24: 260750 | C24: 287584 | D24: 381186 | E24: 442827 | F24: 693727 | G24: 772720 | H24: 709106 | I24: 786715 | J24: 829668 | K24: 890498
A25: Total Equity | B25: 263709 | C25: 293506 | D25: 387112 | E25: 449166 | F25: 700172 | G25: 779485 | H25: 715872 | I25: 793481 | J25: 843200 | K25: 904030
A26: Borrowings (Debt) | B26: 217475 | C26: 239843 | D26: 307714 | E26: 355133 | F26: 278962 | G26: 319158 | H26: 451664 | I26: 350719 | J26: 374313 | K26: 402962
A27: Net Debt (Debt − Cash) | B27: 214452 | C27: 235588 | D27: 296633 | E27: 324213 | F27: 261565 | G27: 282980 | H27: 383000 | I27: 253494 | J27: 267811 | K27: 256985
A28: Net Fixed Assets (Net Block + CWIP) | B28: 523363 | C28: 590907 | D28: 577837 | E28: 641764 | F28: 667211 | G28: 800304 | H28: 1018557 | I28: 1118840 | J28: 1261751 | K28: 1362481
A29: Cash & Bank Balances | B29: 3023 | C29: 4255 | D29: 11081 | E29: 30920 | F29: 17397 | G29: 36178 | H29: 68664 | I29: 97225 | J29: 106502 | K29: 145977
A31: CASH FLOW STATEMENT
B32: FY2017 | C32: FY2018 | D32: FY2019 | E32: FY2020 | F32: FY2021 | G32: FY2022 | H32: FY2023 | I32: FY2024 | J32: FY2025 | K32: FY2026
A33: Cash from Operations (CFO) | B33: 49550 | C33: 71459 | D33: 42346 | E33: 94877 | F33: 26958 | G33: 110654 | H33: 115032 | I33: 158788 | J33: 178703 | K33: 192113
A34: Cash from Investing (CFI) | B34: -66201 | C34: -68192 | D34: -94507 | E34: -72497 | F34: -142385 | G34: -109162 | H34: -93001 | I34: -113581 | J34: -137535 | K34: -101089
A35: Cash from Financing (CFF) | B35: 8617 | C35: -2001 | D35: 55906 | E35: -2541 | F35: 101904 | G35: 17289 | H35: 10455 | I35: -16646 | J35: -31891 | K35: -51549
A36: Free Cash Flow (CFO + CFI) | B36: -16651 | C36: 3267 | D36: -52161 | E36: 22380 | F36: -115427 | G36: 1492 | H36: 22031 | I36: 45207 | J36: 41168 | K36: 91024
A38: KEY METRICS & RATIOS
B39: FY2017 | C39: FY2018 | D39: FY2019 | E39: FY2020 | F39: FY2021 | G39: FY2022 | H39: FY2023 | I39: FY2024 | J39: FY2025 | K39: FY2026
A40: Return on Equity – ROE (%) | B40: 0.1134 | C40: 0.1229 | D40: 0.1023 | E40: 0.0876 | F40: 0.0702 | G40: 0.0779 | H40: 0.0932 | I40: 0.0877 | J40: 0.0826 | K40: 0.0893
A41: Return on Capital Employed – ROCE (%) | B41: 0.072 | C41: 0.0893 | D41: 0.0911 | E41: 0.0834 | F41: 0.0554 | G41: 0.0717 | H41: 0.0874 | I41: 0.0976 | J41: 0.0924 | K41: 0.0929
A42: Net Debt / EBITDA (x) | B42: 4.63 | C42: 3.66 | D42: 3.52 | E42: 3.63 | F42: 3.24 | G42: 2.61 | H42: 2.69 | I42: 1.56 | J42: 1.62 | K42: 1.44
A43: Net Profit Margin (%) | B43: 0.0984 | C43: 0.0923 | D43: 0.0697 | E43: 0.066 | F43: 0.1054 | G43: 0.0874 | H43: 0.0761 | I43: 0.0774 | J43: 0.0723 | K43: 0.0765

Sheet Assumptions
A1: RELIANCE INDUSTRIES LTD | Model Assumptions | ₹ Crores
A4: WACC INPUTS
A5: Risk-Free Rate (10Y G-Sec Yield) | B5: 0.07 | C5: Source: RBI, approx 10Y G-Sec yield
A6: Equity Beta | B6: 0.95 | C6: Source: NSE historical 5Y beta
A7: Equity Risk Premium – ERP | B7: 0.055 | C7: Damodaran India ERP estimate
A8: Cost of Equity [Ke = Rf + β × ERP] | B8: =B5+B6*B7 -> 0.12225
A9: Cost of Debt (Pre-Tax) | B9: 0.075 | C9: Estimated from interest / avg debt
A10: Effective Tax Rate | B10: 0.25 | C10: Estimated based on FY26 PAT/PBT
A11: Cost of Debt (Post-Tax) [Kd × (1−t)] | B11: =B9*(1-B10) -> 0.05625
A12: Market Capitalisation (₹ Cr) | B12: 1772552.6 | C12: Source: Screener.in, Jun 2025
A13: Total Debt (₹ Cr) | B13: 402962 | C13: Source: FY2026 Balance Sheet
A14: Total Capital [MktCap + Debt] | B14: =B12+B13 -> 2175514.6
A15: Weight of Equity [MktCap / Total] | B15: =B12/B14 -> 0.81477394
A16: Weight of Debt [Debt / Total] | B16: =B13/B14 -> 0.18522606
A17: WACC [Ke×We + Kd×Wd] | B17: =B8*B15+B11*B16 -> 0.11002508
A19: REVENUE & MARGIN ASSUMPTIONS (FY27–FY31)
A20: Assumption | B20: FY2027 | C20: FY2028 | D20: FY2029 | E20: FY2030 | F20: FY2031
A21: Revenue Growth (%) | B21: 0.1 | C21: 0.1 | D21: 0.09 | E21: 0.09 | F21: 0.08
A22: EBITDA Margin (%) | B22: 0.175 | C22: 0.175 | D22: 0.175 | E22: 0.18 | F22: 0.18
A23: D&A as % of Revenue | B23: 0.055 | C23: 0.055 | D23: 0.055 | E23: 0.055 | F23: 0.055
A24: Capex as % of Revenue | B24: 0.14 | C24: 0.13 | D24: 0.12 | E24: 0.12 | F24: 0.11
A26: TERMINAL VALUE ASSUMPTIONS
A27: Terminal Growth Rate (g) | B27: 0.05 | C27: Approx. India nominal LT GDP growth
A28: Shares Outstanding (Cr) | B28: 1353.25 | C28: Source: Screener.in, adjusted shares
A29: Current Market Price (₹) | B29: 1309.5 | C29: Source: NSE/BSE, Jun 2025
A30: Net Debt – FY2026 (₹ Cr) | B30: 256985 | C30: Borrowings 402,962 − Cash 145,977

Sheet DCF Valuation
A1: RELIANCE INDUSTRIES LTD | DCF Valuation | ₹ Crores | 5-Year Explicit Forecast (FY27–FY31)
A2: ⚫ Formulas pull from Assumptions sheet | FCFF-based DCF | Year-end discounting
A4: PROJECTED P&L
B5: FY2026A | C5: FY2027E | D5: FY2028E | E5: FY2029E | F5: FY2030E | G5: FY2031E
A6: Revenue | B6: 1055780 | C6: =B6*(1+Assumptions!B21) -> 1161358 | D6: =C6*(1+Assumptions!C21) -> 1277493.8 | E6: =D6*(1+Assumptions!D21) -> 1392468.2 | F6: =E6*(1+Assumptions!E21) -> 1517790.4 | G6: =F6*(1+Assumptions!F21) -> 1639213.6
A7: YoY Revenue Growth (%) | C7: =Assumptions!B21 -> 0.1 | D7: =Assumptions!C21 -> 0.1 | E7: =Assumptions!D21 -> 0.09 | F7: =Assumptions!E21 -> 0.09 | G7: =Assumptions!F21 -> 0.08
A8: EBITDA | B8: 179065 | C8: =C6*Assumptions!B22 -> 203237.65 | D8: =D6*Assumptions!C22 -> 223561.42 | E8: =E6*Assumptions!D22 -> 243681.94 | F8: =F6*Assumptions!E22 -> 273202.27 | G8: =G6*Assumptions!F22 -> 295058.45
A9: EBITDA Margin (%) | B9: =B8/B6 -> 0.16960446 | C9: =Assumptions!B22 -> 0.175 | D9: =Assumptions!C22 -> 0.175 | E9: =Assumptions!D22 -> 0.175 | F9: =Assumptions!E22 -> 0.18 | G9: =Assumptions!F22 -> 0.18
A10: Depreciation & Amortisation (D&A) | B10: 57688 | C10: =C6*Assumptions!B23 -> 63874.69 | D10: =D6*Assumptions!C23 -> 70262.159 | E10: =E6*Assumptions!D23 -> 76585.753 | F10: =F6*Assumptions!E23 -> 83478.471 | G10: =G6*Assumptions!F23 -> 90156.749
A11: EBIT (Operating Profit) | B11: =B8-B10 -> 121377 | C11: =C8-C10 -> 139362.96 | D11: =D8-D10 -> 153299.26 | E11: =E8-E10 -> 167096.19 | F11: =F8-F10 -> 189723.8 | G11: =G8-G10 -> 204901.7
A12: EBIT Margin (%) | B12: =B11/B6 -> 0.11496429 | C12: =C11/C6 -> 0.12 | D12: =D11/D6 -> 0.12 | E12: =E11/E6 -> 0.12 | F12: =F11/F6 -> 0.125 | G12: =G11/G6 -> 0.125
A13: NOPAT [EBIT × (1 − Tax Rate)] | B13: =B11*(1-Assumptions!B10) -> 91032.75 | C13: =C11*(1-Assumptions!B10) -> 104522.22 | D13: =D11*(1-Assumptions!B10) -> 114974.44 | E13: =E11*(1-Assumptions!B10) -> 125322.14 | F13: =F11*(1-Assumptions!B10) -> 142292.85 | G13: =G11*(1-Assumptions!B10) -> 153676.28
A14: Add: D&A | B14: =B10 -> 57688 | C14: =C10 -> 63874.69 | D14: =D10 -> 70262.159 | E14: =E10 -> 76585.753 | F14: =F10 -> 83478.471 | G14: =G10 -> 90156.749
A15: Less: Capital Expenditure (Capex) | C15: =-C6*Assumptions!B24 -> -162590.12 | D15: =-D6*Assumptions!C24 -> -166074.19 | E15: =-E6*Assumptions!D24 -> -167096.19 | F15: =-F6*Assumptions!E24 -> -182134.85 | G15: =-G6*Assumptions!F24 -> -180313.5
A16: FREE CASH FLOW TO FIRM (FCFF) | C16: =C13+C14+C15 -> 5806.79 | D16: =D13+D14+D15 -> 19162.407 | E16: =E13+E14+E15 -> 34811.706 | F16: =F13+F14+F15 -> 43636.474 | G16: =G13+G14+G15 -> 63519.528
A18: DISCOUNTING (Year-End Convention)
A19: Discount Period (years) | C19: 1 | D19: 2 | E19: 3 | F19: 4 | G19: 5
A20: Discount Factor [1 / (1+WACC)^n] | C20: =1/(1+Assumptions!B17)^C19 -> 0.90088055 | D20: =1/(1+Assumptions!B17)^D19 -> 0.81158576 | E20: =1/(1+Assumptions!B17)^E19 -> 0.73114182 | F20: =1/(1+Assumptions!B17)^F19 -> 0.65867144 | G20: =1/(1+Assumptions!B17)^G19 -> 0.59338429
A21: PV of FCFF | C21: =C16*C20 -> 5231.2241 | D21: =D16*D20 -> 15551.937 | E21: =E16*E20 -> 25452.294 | F21: =F16*F20 -> 28742.099 | G21: =G16*G20 -> 37691.49
A22: Sum of PV of FCFFs (A) | B22: =SUM(C21:G21) -> 112669.04
A24: TERMINAL VALUE
A25: Terminal Year FCFF (FY31) | B25: =G16 -> 63519.528
A26: Terminal Growth Rate (g) | B26: =Assumptions!B27 -> 0.05
A27: WACC | B27: =Assumptions!B17 -> 0.11002508
A28: Terminal Value [FCFF × (1+g) / (WACC − g)] | B28: =B25*(1+B26)/(B27-B26) -> 1111127.3
A29: Terminal Value Discount Factor [1/(1+WACC)^5] | B29: =1/(1+Assumptions!B17)^5 -> 0.59338429
A30: PV of Terminal Value (B) | B30: =B28*B29 -> 659325.47
A32: EQUITY VALUE BRIDGE
A33: Enterprise Value [A + B] | B33: =B22+B30 -> 771994.52
A34: Less: Net Debt (FY2026) | B34: =-Assumptions!B30 -> -256985
A35: Equity Value | B35: =B33+B34 -> 515009.52
A36: Shares Outstanding (Cr) | B36: =Assumptions!B28 -> 1353.25
A37: IMPLIED PRICE PER SHARE (₹) | B37: =B35/B36 -> 380.57234
A38: Current Market Price (₹) | B38: =Assumptions!B29 -> 1309.5
A39: Upside / (Downside) vs Market Price (%) | B39: =(B37/B38)-1 -> -0.70937584
A41: 📌 NOTE: Reliance is a diversified conglomerate (O2C, Retail, Jio, New Energy). A single-entity FCFF DCF may undervalue it — a Sum-of-the-Parts (SOTP) model per segment would be the next step in a full analysis.

Sheet Comps
A1: RELIANCE INDUSTRIES LTD | Comparable Company Analysis (Comps)
A2: Source: NSE/BSE, Company Filings | All ₹ Cr | Fill in peer data from Screener.in
A4: Company | B4: Mkt Cap (₹Cr) | C4: EV (₹Cr) | D4: Revenue (₹Cr) | E4: EBITDA (₹Cr) | F4: PAT (₹Cr) | G4: P/E (x) | H4: EV/EBITDA (x) | I4: EV/Sales (x) | J4: ROE (%)
A5: Reliance Industries | B5: 1772552.6 | C5: 2029537.6 | D5: 1055780 | E5: 179065 | F5: 80775 | G5: =B5/F5 -> 21.944322 | H5: =C5/E5 -> 11.334083 | I5: =C5/D5 -> 1.9223111 | J5: 0.0925
A6: Adani Enterprises | B6: 263909 | C6: 347728 | D6: 97895 | E6: 14252 | F6: 8005 | G6: =B6/F6 -> 32.96802 | H6: =C6/E6 -> 24.398541 | I6: =C6/D6 -> 3.5520507 | J6: 0.0982
A7: Tata Motors | B7: 266787 | C7: 303327 | D7: 439695 | E7: 56138 | F7: 28149 | G7: =B7/F7 -> 9.4776724 | H7: =C7/E7 -> 5.4032384 | I7: =C7/D7 -> 0.68985774 | J7: 0.236
A8: Larsen & Toubro | B8: 535675 | C8: 613279 | D8: 255734 | E8: 34427 | F8: 17673 | G8: =B8/F8 -> 30.31036 | H8: =C8/E8 -> 17.813896 | I8: =C8/D8 -> 2.3981129 | J8: 0.159
A9: Bharti Airtel | B9: 1113302 | C9: 1308944 | D9: 172985 | E9: 85060 | F9: 37481 | G9: =B9/F9 -> 29.703103 | H9: =C9/E9 -> 15.388479 | I9: =C9/D9 -> 7.5668064 | J9: 0.232
A10: ITC | B10: 355462 | C10: 321027 | D10: 75323 | E10: 25839 | F10: 20104 | G10: =B10/F10 -> 17.681158 | H10: =C10/E10 -> 12.424126 | I10: =C10/D10 -> 4.262005 | J10: 0.293
A12: Median (Peers) | B12: =MEDIAN(B6:B10) -> 355462 | C12: =MEDIAN(C6:C10) -> 347728 | D12: =MEDIAN(D6:D10) -> 172985 | E12: =MEDIAN(E6:E10) -> 34427 | F12: =MEDIAN(F6:F10) -> 20104 | G12: =MEDIAN(G6:G10) -> 29.703103 | H12: =MEDIAN(H6:H10) -> 15.388479 | I12: =MEDIAN(I6:I10) -> 3.5520507 | J12: =MEDIAN(J6:J10) -> 0.232
A13: 💡 HOW TO USE: Fill in the blue cells with peer data from Screener.in. EV = Mkt Cap + Total Debt − Cash. P/E = Mkt Cap / PAT. EV/EBITDA and EV/Sales compute automatically.

Sheet Sensitivity
A1: RELIANCE INDUSTRIES LTD | Sensitivity Analysis | Implied Price per Share (₹)
A2: Rows: WACC | Columns: Terminal Growth Rate (g) | Base case highlighted in gold
A4: WACC \ g → | B4: 30.0% | C4: 35.0% | D4: 40.0% | E4: 45.0% | F4: 50.0% | G4: 55.0% | H4: 60.0% | I4: 65.0% | J4: 70.0%
A5: 90.0% | B5: -17239.7 | C5: -17190.4 | D5: -17131.3 | E5: -17059 | F5: -16968.6 | G5: -16852.4 | H5: -16697.5 | I5: -16480.6 | J5: -16155.3
A6: 95.0% | B6: -17405.8 | C6: -17368.2 | D6: -17323.8 | E6: -17270.5 | F6: -17205.3 | G6: -17123.9 | H6: -17019.1 | I6: -16879.5 | J6: -16684
A7: 100.0% | B7: -17546.3 | C7: -17517.2 | D7: -17483.2 | E7: -17443.1 | F7: -17394.9 | G7: -17336 | H7: -17262.4 | I7: -17167.8 | J7: -17041.6
A8: 105.0% | B8: -17666.5 | C8: -17643.6 | D8: -17617.3 | E8: -17586.5 | F8: -17550.1 | G8: -17506.5 | H8: -17453.1 | I8: -17386.4 | J8: -17300.7
A9: 110.0% | B9: -17770.3 | C9: -17752.2 | D9: -17731.4 | E9: -17707.5 | F9: -17679.5 | G9: -17646.5 | H9: -17606.8 | I9: -17558.4 | J9: -17497.8
A10: 115.0% | B10: -17860.8 | C10: -17846.2 | D10: -17829.7 | E10: -17810.8 | F10: -17789 | G10: -17763.5 | H10: -17733.5 | I10: -17697.4 | J10: -17653.3
A11: 120.0% | B11: -17940.2 | C11: -17928.4 | D11: -17915.1 | E11: -17900 | F11: -17882.8 | G11: -17862.9 | H11: -17839.7 | I11: -17812.3 | J11: -17779.3
A12: 125.0% | B12: -18010.4 | C12: -18000.7 | D12: -17989.9 | E12: -17977.8 | F12: -17964 | G12: -17948.2 | H12: -17930 | I12: -17908.8 | J12: -17883.8
A13: 130.0% | B13: -18072.8 | C13: -18064.9 | D13: -18056 | E13: -18046.1 | F13: -18035 | G13: -18022.3 | H13: -18007.9 | I13: -17991.3 | J13: -17971.8
A15: Base case: WACC = 11%, g = 5%. Current market price: ₹1,309.5. Light blue cells = implied price exceeds current market price (upside scenarios). Gap vs market price reflects Reliance's embedded growth optionality (Jio, Retail, New Energy).
